{"is_source_file": true, "format": "Python", "description": "This file defines an API view for a health check endpoint in a Django application, responding with a simple message indicating the server status.", "external_files": ["rest_framework.decorators", "rest_framework.response"], "external_methods": ["api_view", "Response"], "published": [], "classes": [], "methods": [{"name": "health(request)", "description": "A Django REST framework view that handles GET requests to return the server status.", "scope": "", "scopeKind": ""}], "calls": ["rest_framework.response.Response"], "search-terms": ["Django", "API view", "health check"], "state": 2, "file_id": 7, "knowledge_revision": 29, "git_revision": "b746a51d1303b2e81fdf81573fc128e0793dfe1e", "ctags": [{"_type": "tag", "name": "health", "path": "/tmp/kavia/workspace/code-generation/hello-world-application-4298-4308/django_backend/api/views.py", "pattern": "/^def health(request):$/", "language": "Python", "kind": "function", "signature": "(request)"}], "hash": "e3ccd8059b968c2eaeb07756801c967e", "format-version": 4, "code-base-name": "django_backend", "filename": "django_backend/api/views.py", "revision_history": [{"29": "b746a51d1303b2e81fdf81573fc128e0793dfe1e"}]}